{
    "type": "FeatureCollection",
    "features": [
        {
            "type": "Feature",
            "geometry": {
                "type": "Point",
                "coordinates": [
                    -111.8152857,
                    41.7275276
                ]
            },
            "properties": {
                "observation_date": "2005-03-09",
                "species_reported": "0"
            }
        },
        {
            "type": "Feature",
            "geometry": {
                "type": "Point",
                "coordinates": [
                    -111.53097,
                    40.18078
                ]
            },
            "properties": {
                "observation_date": "2005-03-12",
                "species_reported": "0"
            }
        },
        {
            "type": "Feature",
            "geometry": {
                "type": "Point",
                "coordinates": [
                    -110.1621437,
                    38.9953732
                ]
            },
            "properties": {
                "observation_date": "2005-03-27",
                "species_reported": "0"
            }
        },
        {
            "type": "Feature",
            "geometry": {
                "type": "Point",
                "coordinates": [
                    -111.6560912,
                    40.5815549
                ]
            },
            "properties": {
                "observation_date": "2005-03-02",
                "species_reported": "1"
            }
        },
        {
            "type": "Feature",
            "geometry": {
                "type": "Point",
                "coordinates": [
                    -109.5288849,
                    40.4573971
                ]
            },
            "properties": {
                "observation_date": "2005-03-27",
                "species_reported": "0"
            }
        },
        {
            "type": "Feature",
            "geometry": {
                "type": "Point",
                "coordinates": [
                    -109.860878,
                    38.2721495
                ]
            },
            "properties": {
                "observation_date": "2005-03-26",
                "species_reported": "0"
            }
        },
        {
            "type": "Feature",
            "geometry": {
                "type": "Point",
                "coordinates": [
                    -109.5409118,
                    38.6094554
                ]
            },
            "properties": {
                "observation_date": "2005-03-26",
                "species_reported": "1"
            }
        },
        {
            "type": "Feature",
            "geometry": {
                "type": "Point",
                "coordinates": [
                    -109.94185,
                    37.27602
                ]
            },
            "properties": {
                "observation_date": "2005-03-12",
                "species_reported": "1"
            }
        },
        {
            "type": "Feature",
            "geometry": {
                "type": "Point",
                "coordinates": [
                    -113.98283,
                    39.44994
                ]
            },
            "properties": {
                "observation_date": "2005-03-17",
                "species_reported": "0"
            }
        },
        {
            "type": "Feature",
            "geometry": {
                "type": "Point",
                "coordinates": [
                    -113.9187384,
                    39.4834416
                ]
            },
            "properties": {
                "observation_date": "2005-03-10",
                "species_reported": "0"
            }
        },
        {
            "type": "Feature",
            "geometry": {
                "type": "Point",
                "coordinates": [
                    -113.9187384,
                    39.4834416
                ]
            },
            "properties": {
                "observation_date": "2005-03-30",
                "species_reported": "0"
            }
        },
        {
            "type": "Feature",
            "geometry": {
                "type": "Point",
                "coordinates": [
                    -113.8811016,
                    39.412108
                ]
            },
            "properties": {
                "observation_date": "2005-03-03",
                "species_reported": "0"
            }
        },
        {
            "type": "Feature",
            "geometry": {
                "type": "Point",
                "coordinates": [
                    -113.8811016,
                    39.412108
                ]
            },
            "properties": {
                "observation_date": "2005-03-14",
                "species_reported": "0"
            }
        },
        {
            "type": "Feature",
            "geometry": {
                "type": "Point",
                "coordinates": [
                    -113.8811016,
                    39.412108
                ]
            },
            "properties": {
                "observation_date": "2005-03-15",
                "species_reported": "0"
            }
        },
        {
            "type": "Feature",
            "geometry": {
                "type": "Point",
                "coordinates": [
                    -113.8811016,
                    39.412108
                ]
            },
            "properties": {
                "observation_date": "2005-03-31",
                "species_reported": "0"
            }
        },
        {
            "type": "Feature",
            "geometry": {
                "type": "Point",
                "coordinates": [
                    -112.41077,
                    38.88577
                ]
            },
            "properties": {
                "observation_date": "2005-03-05",
                "species_reported": "0"
            }
        },
        {
            "type": "Feature",
            "geometry": {
                "type": "Point",
                "coordinates": [
                    -112.41077,
                    38.88577
                ]
            },
            "properties": {
                "observation_date": "2005-03-05",
                "species_reported": "0"
            }
        },
        {
            "type": "Feature",
            "geometry": {
                "type": "Point",
                "coordinates": [
                    -113.8417885,
                    38.6150563
                ]
            },
            "properties": {
                "observation_date": "2005-03-02",
                "species_reported": "0"
            }
        },
        {
            "type": "Feature",
            "geometry": {
                "type": "Point",
                "coordinates": [
                    -112.4412918,
                    39.2553147
                ]
            },
            "properties": {
                "observation_date": "2005-03-05",
                "species_reported": "0"
            }
        },
        {
            "type": "Feature",
            "geometry": {
                "type": "Point",
                "coordinates": [
                    -112.4412918,
                    39.2553147
                ]
            },
            "properties": {
                "observation_date": "2005-03-05",
                "species_reported": "0"
            }
        },
        {
            "type": "Feature",
            "geometry": {
                "type": "Point",
                "coordinates": [
                    -112.43777,
                    38.80137
                ]
            },
            "properties": {
                "observation_date": "2005-03-05",
                "species_reported": "0"
            }
        },
        {
            "type": "Feature",
            "geometry": {
                "type": "Point",
                "coordinates": [
                    -112.43777,
                    38.80137
                ]
            },
            "properties": {
                "observation_date": "2005-03-05",
                "species_reported": "0"
            }
        },
        {
            "type": "Feature",
            "geometry": {
                "type": "Point",
                "coordinates": [
                    -112.65278,
                    39.28686
                ]
            },
            "properties": {
                "observation_date": "2005-03-05",
                "species_reported": "0"
            }
        },
        {
            "type": "Feature",
            "geometry": {
                "type": "Point",
                "coordinates": [
                    -112.65278,
                    39.28686
                ]
            },
            "properties": {
                "observation_date": "2005-03-05",
                "species_reported": "0"
            }
        },
        {
            "type": "Feature",
            "geometry": {
                "type": "Point",
                "coordinates": [
                    -112.6671982,
                    39.2361711
                ]
            },
            "properties": {
                "observation_date": "2005-03-05",
                "species_reported": "0"
            }
        },
        {
            "type": "Feature",
            "geometry": {
                "type": "Point",
                "coordinates": [
                    -112.6671982,
                    39.2361711
                ]
            },
            "properties": {
                "observation_date": "2005-03-05",
                "species_reported": "0"
            }
        },
        {
            "type": "Feature",
            "geometry": {
                "type": "Point",
                "coordinates": [
                    -112.9654984,
                    37.2285636
                ]
            },
            "properties": {
                "observation_date": "2005-03-05",
                "species_reported": "0"
            }
        },
        {
            "type": "Feature",
            "geometry": {
                "type": "Point",
                "coordinates": [
                    -112.9654984,
                    37.2285636
                ]
            },
            "properties": {
                "observation_date": "2005-03-12",
                "species_reported": "0"
            }
        },
        {
            "type": "Feature",
            "geometry": {
                "type": "Point",
                "coordinates": [
                    -112.9654984,
                    37.2285636
                ]
            },
            "properties": {
                "observation_date": "2005-03-29",
                "species_reported": "1"
            }
        },
        {
            "type": "Feature",
            "geometry": {
                "type": "Point",
                "coordinates": [
                    -112.9654984,
                    37.2285636
                ]
            },
            "properties": {
                "observation_date": "2005-03-15",
                "species_reported": "1"
            }
        },
        {
            "type": "Feature",
            "geometry": {
                "type": "Point",
                "coordinates": [
                    -112.9654984,
                    37.2285636
                ]
            },
            "properties": {
                "observation_date": "2005-03-28",
                "species_reported": "1"
            }
        },
        {
            "type": "Feature",
            "geometry": {
                "type": "Point",
                "coordinates": [
                    -112.9654984,
                    37.2285636
                ]
            },
            "properties": {
                "observation_date": "2005-03-12",
                "species_reported": "0"
            }
        },
        {
            "type": "Feature",
            "geometry": {
                "type": "Point",
                "coordinates": [
                    -112.9654984,
                    37.2285636
                ]
            },
            "properties": {
                "observation_date": "2005-03-26",
                "species_reported": "0"
            }
        },
        {
            "type": "Feature",
            "geometry": {
                "type": "Point",
                "coordinates": [
                    -112.9654984,
                    37.2285636
                ]
            },
            "properties": {
                "observation_date": "2005-03-25",
                "species_reported": "0"
            }
        },
        {
            "type": "Feature",
            "geometry": {
                "type": "Point",
                "coordinates": [
                    -112.9654984,
                    37.2285636
                ]
            },
            "properties": {
                "observation_date": "2005-03-19",
                "species_reported": "0"
            }
        },
        {
            "type": "Feature",
            "geometry": {
                "type": "Point",
                "coordinates": [
                    -112.9654984,
                    37.2285636
                ]
            },
            "properties": {
                "observation_date": "2005-03-28",
                "species_reported": "1"
            }
        },
        {
            "type": "Feature",
            "geometry": {
                "type": "Point",
                "coordinates": [
                    -112.9654984,
                    37.2285636
                ]
            },
            "properties": {
                "observation_date": "2005-03-28",
                "species_reported": "1"
            }
        },
        {
            "type": "Feature",
            "geometry": {
                "type": "Point",
                "coordinates": [
                    -113.3774948,
                    37.2346077
                ]
            },
            "properties": {
                "observation_date": "2005-03-24",
                "species_reported": "1"
            }
        },
        {
            "type": "Feature",
            "geometry": {
                "type": "Point",
                "coordinates": [
                    -113.3774948,
                    37.2346077
                ]
            },
            "properties": {
                "observation_date": "2005-03-29",
                "species_reported": "1"
            }
        },
        {
            "type": "Feature",
            "geometry": {
                "type": "Point",
                "coordinates": [
                    -113.3774948,
                    37.2346077
                ]
            },
            "properties": {
                "observation_date": "2005-03-08",
                "species_reported": "1"
            }
        },
        {
            "type": "Feature",
            "geometry": {
                "type": "Point",
                "coordinates": [
                    -113.3774948,
                    37.2346077
                ]
            },
            "properties": {
                "observation_date": "2005-03-01",
                "species_reported": "1"
            }
        },
        {
            "type": "Feature",
            "geometry": {
                "type": "Point",
                "coordinates": [
                    -113.3774948,
                    37.2346077
                ]
            },
            "properties": {
                "observation_date": "2005-03-13",
                "species_reported": "0"
            }
        },
        {
            "type": "Feature",
            "geometry": {
                "type": "Point",
                "coordinates": [
                    -112.2390532,
                    41.0614917
                ]
            },
            "properties": {
                "observation_date": "2005-03-17",
                "species_reported": "0"
            }
        },
        {
            "type": "Feature",
            "geometry": {
                "type": "Point",
                "coordinates": [
                    -109.8025551,
                    38.1467224
                ]
            },
            "properties": {
                "observation_date": "2005-03-26",
                "species_reported": "0"
            }
        },
        {
            "type": "Feature",
            "geometry": {
                "type": "Point",
                "coordinates": [
                    -112.3445823,
                    38.9647437
                ]
            },
            "properties": {
                "observation_date": "2005-03-10",
                "species_reported": "0"
            }
        },
        {
            "type": "Feature",
            "geometry": {
                "type": "Point",
                "coordinates": [
                    -112.9927538,
                    37.9336177
                ]
            },
            "properties": {
                "observation_date": "2005-03-09",
                "species_reported": "1"
            }
        },
        {
            "type": "Feature",
            "geometry": {
                "type": "Point",
                "coordinates": [
                    -109.856707,
                    38.3124036
                ]
            },
            "properties": {
                "observation_date": "2005-03-26",
                "species_reported": "0"
            }
        },
        {
            "type": "Feature",
            "geometry": {
                "type": "Point",
                "coordinates": [
                    -111.988205,
                    41.218197
                ]
            },
            "properties": {
                "observation_date": "2005-03-16",
                "species_reported": "1"
            }
        },
        {
            "type": "Feature",
            "geometry": {
                "type": "Point",
                "coordinates": [
                    -112.186714,
                    41.08841
                ]
            },
            "properties": {
                "observation_date": "2005-03-06",
                "species_reported": "1"
            }
        },
        {
            "type": "Feature",
            "geometry": {
                "type": "Point",
                "coordinates": [
                    -112.186714,
                    41.08841
                ]
            },
            "properties": {
                "observation_date": "2005-03-13",
                "species_reported": "1"
            }
        },
        {
            "type": "Feature",
            "geometry": {
                "type": "Point",
                "coordinates": [
                    -112.9765777,
                    37.2122648
                ]
            },
            "properties": {
                "observation_date": "2005-03-12",
                "species_reported": "1"
            }
        },
        {
            "type": "Feature",
            "geometry": {
                "type": "Point",
                "coordinates": [
                    -111.9544,
                    41.2358
                ]
            },
            "properties": {
                "observation_date": "2005-03-26",
                "species_reported": "1"
            }
        },
        {
            "type": "Feature",
            "geometry": {
                "type": "Point",
                "coordinates": [
                    -113.77344,
                    37.262695
                ]
            },
            "properties": {
                "observation_date": "2005-03-31",
                "species_reported": "1"
            }
        },
        {
            "type": "Feature",
            "geometry": {
                "type": "Point",
                "coordinates": [
                    -112.2947788,
                    41.4692291
                ]
            },
            "properties": {
                "observation_date": "2005-03-08",
                "species_reported": "1"
            }
        },
        {
            "type": "Feature",
            "geometry": {
                "type": "Point",
                "coordinates": [
                    -112.2947788,
                    41.4692291
                ]
            },
            "properties": {
                "observation_date": "2005-03-15",
                "species_reported": "1"
            }
        },
        {
            "type": "Feature",
            "geometry": {
                "type": "Point",
                "coordinates": [
                    -112.2947788,
                    41.4692291
                ]
            },
            "properties": {
                "observation_date": "2005-03-26",
                "species_reported": "0"
            }
        },
        {
            "type": "Feature",
            "geometry": {
                "type": "Point",
                "coordinates": [
                    -112.2947788,
                    41.4692291
                ]
            },
            "properties": {
                "observation_date": "2005-03-08",
                "species_reported": "0"
            }
        },
        {
            "type": "Feature",
            "geometry": {
                "type": "Point",
                "coordinates": [
                    -112.2947788,
                    41.4692291
                ]
            },
            "properties": {
                "observation_date": "2005-03-15",
                "species_reported": "0"
            }
        },
        {
            "type": "Feature",
            "geometry": {
                "type": "Point",
                "coordinates": [
                    -111.9191396,
                    40.955141
                ]
            },
            "properties": {
                "observation_date": "2005-03-27",
                "species_reported": "1"
            }
        },
        {
            "type": "Feature",
            "geometry": {
                "type": "Point",
                "coordinates": [
                    -111.9525719,
                    41.787153
                ]
            },
            "properties": {
                "observation_date": "2005-03-18",
                "species_reported": "1"
            }
        },
        {
            "type": "Feature",
            "geometry": {
                "type": "Point",
                "coordinates": [
                    -111.9525719,
                    41.787153
                ]
            },
            "properties": {
                "observation_date": "2005-03-18",
                "species_reported": "1"
            }
        },
        {
            "type": "Feature",
            "geometry": {
                "type": "Point",
                "coordinates": [
                    -111.2196009,
                    38.284879
                ]
            },
            "properties": {
                "observation_date": "2005-03-16",
                "species_reported": "0"
            }
        },
        {
            "type": "Feature",
            "geometry": {
                "type": "Point",
                "coordinates": [
                    -111.855865,
                    40.705223
                ]
            },
            "properties": {
                "observation_date": "2005-03-18",
                "species_reported": "1"
            }
        },
        {
            "type": "Feature",
            "geometry": {
                "type": "Point",
                "coordinates": [
                    -111.855865,
                    40.705223
                ]
            },
            "properties": {
                "observation_date": "2005-03-05",
                "species_reported": "1"
            }
        },
        {
            "type": "Feature",
            "geometry": {
                "type": "Point",
                "coordinates": [
                    -111.9911629,
                    41.1924951
                ]
            },
            "properties": {
                "observation_date": "2005-03-23",
                "species_reported": "1"
            }
        },
        {
            "type": "Feature",
            "geometry": {
                "type": "Point",
                "coordinates": [
                    -111.93015,
                    41.09755
                ]
            },
            "properties": {
                "observation_date": "2005-03-09",
                "species_reported": "1"
            }
        },
        {
            "type": "Feature",
            "geometry": {
                "type": "Point",
                "coordinates": [
                    -111.82477,
                    40.66885
                ]
            },
            "properties": {
                "observation_date": "2005-03-29",
                "species_reported": "0"
            }
        },
        {
            "type": "Feature",
            "geometry": {
                "type": "Point",
                "coordinates": [
                    -111.82477,
                    40.66885
                ]
            },
            "properties": {
                "observation_date": "2005-03-30",
                "species_reported": "0"
            }
        },
        {
            "type": "Feature",
            "geometry": {
                "type": "Point",
                "coordinates": [
                    -111.49775,
                    40.64605
                ]
            },
            "properties": {
                "observation_date": "2005-03-15",
                "species_reported": "0"
            }
        },
        {
            "type": "Feature",
            "geometry": {
                "type": "Point",
                "coordinates": [
                    -112.1680972,
                    40.9234737
                ]
            },
            "properties": {
                "observation_date": "2005-03-22",
                "species_reported": "0"
            }
        },
        {
            "type": "Feature",
            "geometry": {
                "type": "Point",
                "coordinates": [
                    -113.0005646,
                    37.1833562
                ]
            },
            "properties": {
                "observation_date": "2005-03-17",
                "species_reported": "0"
            }
        },
        {
            "type": "Feature",
            "geometry": {
                "type": "Point",
                "coordinates": [
                    -112.0848239,
                    38.7725252
                ]
            },
            "properties": {
                "observation_date": "2005-03-25",
                "species_reported": "1"
            }
        },
        {
            "type": "Feature",
            "geometry": {
                "type": "Point",
                "coordinates": [
                    -111.9379788,
                    41.22524
                ]
            },
            "properties": {
                "observation_date": "2005-03-16",
                "species_reported": "1"
            }
        },
        {
            "type": "Feature",
            "geometry": {
                "type": "Point",
                "coordinates": [
                    -111.9379788,
                    41.22524
                ]
            },
            "properties": {
                "observation_date": "2005-03-20",
                "species_reported": "1"
            }
        },
        {
            "type": "Feature",
            "geometry": {
                "type": "Point",
                "coordinates": [
                    -112.986324,
                    37.2001453
                ]
            },
            "properties": {
                "observation_date": "2005-03-05",
                "species_reported": "1"
            }
        },
        {
            "type": "Feature",
            "geometry": {
                "type": "Point",
                "coordinates": [
                    -112.986324,
                    37.2001453
                ]
            },
            "properties": {
                "observation_date": "2005-03-04",
                "species_reported": "1"
            }
        },
        {
            "type": "Feature",
            "geometry": {
                "type": "Point",
                "coordinates": [
                    -112.6812744,
                    39.3459805
                ]
            },
            "properties": {
                "observation_date": "2005-03-11",
                "species_reported": "0"
            }
        },
        {
            "type": "Feature",
            "geometry": {
                "type": "Point",
                "coordinates": [
                    -111.6446943,
                    40.2237592
                ]
            },
            "properties": {
                "observation_date": "2005-03-08",
                "species_reported": "1"
            }
        },
        {
            "type": "Feature",
            "geometry": {
                "type": "Point",
                "coordinates": [
                    -109.57506,
                    38.57783
                ]
            },
            "properties": {
                "observation_date": "2005-03-22",
                "species_reported": "1"
            }
        },
        {
            "type": "Feature",
            "geometry": {
                "type": "Point",
                "coordinates": [
                    -109.57506,
                    38.57783
                ]
            },
            "properties": {
                "observation_date": "2005-03-19",
                "species_reported": "1"
            }
        },
        {
            "type": "Feature",
            "geometry": {
                "type": "Point",
                "coordinates": [
                    -109.53313,
                    38.60895
                ]
            },
            "properties": {
                "observation_date": "2005-03-21",
                "species_reported": "1"
            }
        },
        {
            "type": "Feature",
            "geometry": {
                "type": "Point",
                "coordinates": [
                    -109.31141,
                    38.88989
                ]
            },
            "properties": {
                "observation_date": "2005-03-29",
                "species_reported": "1"
            }
        },
        {
            "type": "Feature",
            "geometry": {
                "type": "Point",
                "coordinates": [
                    -112.57678,
                    39.35216
                ]
            },
            "properties": {
                "observation_date": "2005-03-05",
                "species_reported": "0"
            }
        },
        {
            "type": "Feature",
            "geometry": {
                "type": "Point",
                "coordinates": [
                    -112.57678,
                    39.35216
                ]
            },
            "properties": {
                "observation_date": "2005-03-05",
                "species_reported": "0"
            }
        },
        {
            "type": "Feature",
            "geometry": {
                "type": "Point",
                "coordinates": [
                    -112.25878,
                    40.36935
                ]
            },
            "properties": {
                "observation_date": "2005-03-12",
                "species_reported": "1"
            }
        },
        {
            "type": "Feature",
            "geometry": {
                "type": "Point",
                "coordinates": [
                    -109.94386,
                    37.39651
                ]
            },
            "properties": {
                "observation_date": "2005-03-12",
                "species_reported": "0"
            }
        },
        {
            "type": "Feature",
            "geometry": {
                "type": "Point",
                "coordinates": [
                    -112.7080412,
                    39.3588826
                ]
            },
            "properties": {
                "observation_date": "2005-03-05",
                "species_reported": "0"
            }
        },
        {
            "type": "Feature",
            "geometry": {
                "type": "Point",
                "coordinates": [
                    -112.617658,
                    39.3528238
                ]
            },
            "properties": {
                "observation_date": "2005-03-05",
                "species_reported": "0"
            }
        },
        {
            "type": "Feature",
            "geometry": {
                "type": "Point",
                "coordinates": [
                    -112.617658,
                    39.3528238
                ]
            },
            "properties": {
                "observation_date": "2005-03-04",
                "species_reported": "1"
            }
        },
        {
            "type": "Feature",
            "geometry": {
                "type": "Point",
                "coordinates": [
                    -112.617658,
                    39.3528238
                ]
            },
            "properties": {
                "observation_date": "2005-03-05",
                "species_reported": "0"
            }
        },
        {
            "type": "Feature",
            "geometry": {
                "type": "Point",
                "coordinates": [
                    -112.617658,
                    39.3528238
                ]
            },
            "properties": {
                "observation_date": "2005-03-05",
                "species_reported": "0"
            }
        },
        {
            "type": "Feature",
            "geometry": {
                "type": "Point",
                "coordinates": [
                    -112.4155556,
                    40.4589167
                ]
            },
            "properties": {
                "observation_date": "2005-03-19",
                "species_reported": "1"
            }
        },
        {
            "type": "Feature",
            "geometry": {
                "type": "Point",
                "coordinates": [
                    -112.0255668,
                    41.0403388
                ]
            },
            "properties": {
                "observation_date": "2005-03-27",
                "species_reported": "0"
            }
        },
        {
            "type": "Feature",
            "geometry": {
                "type": "Point",
                "coordinates": [
                    -113.3767755,
                    37.1162993
                ]
            },
            "properties": {
                "observation_date": "2005-03-01",
                "species_reported": "1"
            }
        },
        {
            "type": "Feature",
            "geometry": {
                "type": "Point",
                "coordinates": [
                    -112.29878,
                    40.53074
                ]
            },
            "properties": {
                "observation_date": "2005-03-12",
                "species_reported": "1"
            }
        },
        {
            "type": "Feature",
            "geometry": {
                "type": "Point",
                "coordinates": [
                    -111.9018137,
                    41.0241293
                ]
            },
            "properties": {
                "observation_date": "2005-03-14",
                "species_reported": "0"
            }
        },
        {
            "type": "Feature",
            "geometry": {
                "type": "Point",
                "coordinates": [
                    -111.9018137,
                    41.0241293
                ]
            },
            "properties": {
                "observation_date": "2005-03-14",
                "species_reported": "0"
            }
        },
        {
            "type": "Feature",
            "geometry": {
                "type": "Point",
                "coordinates": [
                    -113.3698087,
                    37.1744708
                ]
            },
            "properties": {
                "observation_date": "2005-03-01",
                "species_reported": "1"
            }
        },
        {
            "type": "Feature",
            "geometry": {
                "type": "Point",
                "coordinates": [
                    -112.5503182,
                    40.3466095
                ]
            },
            "properties": {
                "observation_date": "2005-03-12",
                "species_reported": "1"
            }
        },
        {
            "type": "Feature",
            "geometry": {
                "type": "Point",
                "coordinates": [
                    -112.5503182,
                    40.3466095
                ]
            },
            "properties": {
                "observation_date": "2005-03-12",
                "species_reported": "1"
            }
        },
        {
            "type": "Feature",
            "geometry": {
                "type": "Point",
                "coordinates": [
                    -111.9386694,
                    41.18395
                ]
            },
            "properties": {
                "observation_date": "2005-03-05",
                "species_reported": "1"
            }
        },
        {
            "type": "Feature",
            "geometry": {
                "type": "Point",
                "coordinates": [
                    -113.3936175,
                    39.865343
                ]
            },
            "properties": {
                "observation_date": "2005-03-05",
                "species_reported": "1"
            }
        },
        {
            "type": "Feature",
            "geometry": {
                "type": "Point",
                "coordinates": [
                    -113.3190823,
                    37.1318215
                ]
            },
            "properties": {
                "observation_date": "2005-03-16",
                "species_reported": "1"
            }
        },
        {
            "type": "Feature",
            "geometry": {
                "type": "Point",
                "coordinates": [
                    -112.33578,
                    39.37496
                ]
            },
            "properties": {
                "observation_date": "2005-03-05",
                "species_reported": "0"
            }
        },
        {
            "type": "Feature",
            "geometry": {
                "type": "Point",
                "coordinates": [
                    -112.33578,
                    39.37496
                ]
            },
            "properties": {
                "observation_date": "2005-03-05",
                "species_reported": "0"
            }
        },
        {
            "type": "Feature",
            "geometry": {
                "type": "Point",
                "coordinates": [
                    -113.5134888,
                    37.0913353
                ]
            },
            "properties": {
                "observation_date": "2005-03-16",
                "species_reported": "1"
            }
        },
        {
            "type": "Feature",
            "geometry": {
                "type": "Point",
                "coordinates": [
                    -113.579793,
                    37.0901713
                ]
            },
            "properties": {
                "observation_date": "2005-03-29",
                "species_reported": "1"
            }
        },
        {
            "type": "Feature",
            "geometry": {
                "type": "Point",
                "coordinates": [
                    -111.4280426,
                    40.5858627
                ]
            },
            "properties": {
                "observation_date": "2005-03-17",
                "species_reported": "0"
            }
        },
        {
            "type": "Feature",
            "geometry": {
                "type": "Point",
                "coordinates": [
                    -111.4874339,
                    38.2832669
                ]
            },
            "properties": {
                "observation_date": "2005-03-25",
                "species_reported": "0"
            }
        },
        {
            "type": "Feature",
            "geometry": {
                "type": "Point",
                "coordinates": [
                    -109.596203,
                    38.593554
                ]
            },
            "properties": {
                "observation_date": "2005-03-20",
                "species_reported": "0"
            }
        },
        {
            "type": "Feature",
            "geometry": {
                "type": "Point",
                "coordinates": [
                    -109.8141137,
                    38.1803865
                ]
            },
            "properties": {
                "observation_date": "2005-03-14",
                "species_reported": "1"
            }
        },
        {
            "type": "Feature",
            "geometry": {
                "type": "Point",
                "coordinates": [
                    -109.8141137,
                    38.1803865
                ]
            },
            "properties": {
                "observation_date": "2005-03-15",
                "species_reported": "1"
            }
        },
        {
            "type": "Feature",
            "geometry": {
                "type": "Point",
                "coordinates": [
                    -111.9374228,
                    41.09685
                ]
            },
            "properties": {
                "observation_date": "2005-03-12",
                "species_reported": "1"
            }
        },
        {
            "type": "Feature",
            "geometry": {
                "type": "Point",
                "coordinates": [
                    -111.7218187,
                    40.3646535
                ]
            },
            "properties": {
                "observation_date": "2005-03-07",
                "species_reported": "0"
            }
        },
        {
            "type": "Feature",
            "geometry": {
                "type": "Point",
                "coordinates": [
                    -111.7218187,
                    40.3646535
                ]
            },
            "properties": {
                "observation_date": "2005-03-21",
                "species_reported": "1"
            }
        },
        {
            "type": "Feature",
            "geometry": {
                "type": "Point",
                "coordinates": [
                    -111.7218187,
                    40.3646535
                ]
            },
            "properties": {
                "observation_date": "2005-03-14",
                "species_reported": "1"
            }
        },
        {
            "type": "Feature",
            "geometry": {
                "type": "Point",
                "coordinates": [
                    -111.7218187,
                    40.3646535
                ]
            },
            "properties": {
                "observation_date": "2005-03-27",
                "species_reported": "1"
            }
        },
        {
            "type": "Feature",
            "geometry": {
                "type": "Point",
                "coordinates": [
                    -112.09277,
                    40.26215
                ]
            },
            "properties": {
                "observation_date": "2005-03-12",
                "species_reported": "1"
            }
        },
        {
            "type": "Feature",
            "geometry": {
                "type": "Point",
                "coordinates": [
                    -112.4198341,
                    40.1822177
                ]
            },
            "properties": {
                "observation_date": "2005-03-12",
                "species_reported": "1"
            }
        },
        {
            "type": "Feature",
            "geometry": {
                "type": "Point",
                "coordinates": [
                    -112.0941067,
                    40.260763
                ]
            },
            "properties": {
                "observation_date": "2005-03-12",
                "species_reported": "1"
            }
        },
        {
            "type": "Feature",
            "geometry": {
                "type": "Point",
                "coordinates": [
                    -113.20467,
                    37.6528735
                ]
            },
            "properties": {
                "observation_date": "2005-03-02",
                "species_reported": "1"
            }
        },
        {
            "type": "Feature",
            "geometry": {
                "type": "Point",
                "coordinates": [
                    -113.20467,
                    37.6528735
                ]
            },
            "properties": {
                "observation_date": "2005-03-04",
                "species_reported": "1"
            }
        },
        {
            "type": "Feature",
            "geometry": {
                "type": "Point",
                "coordinates": [
                    -111.7104328,
                    40.375288
                ]
            },
            "properties": {
                "observation_date": "2005-03-10",
                "species_reported": "1"
            }
        },
        {
            "type": "Feature",
            "geometry": {
                "type": "Point",
                "coordinates": [
                    -111.5303236,
                    38.305363
                ]
            },
            "properties": {
                "observation_date": "2005-03-25",
                "species_reported": "0"
            }
        },
        {
            "type": "Feature",
            "geometry": {
                "type": "Point",
                "coordinates": [
                    -111.8021107,
                    40.3431833
                ]
            },
            "properties": {
                "observation_date": "2005-03-14",
                "species_reported": "1"
            }
        },
        {
            "type": "Feature",
            "geometry": {
                "type": "Point",
                "coordinates": [
                    -112.2406518,
                    40.3785001
                ]
            },
            "properties": {
                "observation_date": "2005-03-12",
                "species_reported": "1"
            }
        },
        {
            "type": "Feature",
            "geometry": {
                "type": "Point",
                "coordinates": [
                    -112.2665244,
                    39.3504068
                ]
            },
            "properties": {
                "observation_date": "2005-03-05",
                "species_reported": "0"
            }
        },
        {
            "type": "Feature",
            "geometry": {
                "type": "Point",
                "coordinates": [
                    -112.2665244,
                    39.3504068
                ]
            },
            "properties": {
                "observation_date": "2005-03-05",
                "species_reported": "0"
            }
        },
        {
            "type": "Feature",
            "geometry": {
                "type": "Point",
                "coordinates": [
                    -111.6503298,
                    40.188447
                ]
            },
            "properties": {
                "observation_date": "2005-03-20",
                "species_reported": "0"
            }
        },
        {
            "type": "Feature",
            "geometry": {
                "type": "Point",
                "coordinates": [
                    -111.9609833,
                    39.4897346
                ]
            },
            "properties": {
                "observation_date": "2005-03-19",
                "species_reported": "1"
            }
        },
        {
            "type": "Feature",
            "geometry": {
                "type": "Point",
                "coordinates": [
                    -112.1058655,
                    39.2949855
                ]
            },
            "properties": {
                "observation_date": "2005-03-19",
                "species_reported": "1"
            }
        },
        {
            "type": "Feature",
            "geometry": {
                "type": "Point",
                "coordinates": [
                    -112.27077,
                    39.09886
                ]
            },
            "properties": {
                "observation_date": "2005-03-19",
                "species_reported": "1"
            }
        },
        {
            "type": "Feature",
            "geometry": {
                "type": "Point",
                "coordinates": [
                    -113.6412048,
                    37.2122847
                ]
            },
            "properties": {
                "observation_date": "2005-03-31",
                "species_reported": "1"
            }
        },
        {
            "type": "Feature",
            "geometry": {
                "type": "Point",
                "coordinates": [
                    -113.6412048,
                    37.2122847
                ]
            },
            "properties": {
                "observation_date": "2005-03-29",
                "species_reported": "1"
            }
        },
        {
            "type": "Feature",
            "geometry": {
                "type": "Point",
                "coordinates": [
                    -111.8619776,
                    40.6340172
                ]
            },
            "properties": {
                "observation_date": "2005-03-02",
                "species_reported": "1"
            }
        },
        {
            "type": "Feature",
            "geometry": {
                "type": "Point",
                "coordinates": [
                    -109.5508146,
                    38.5774603
                ]
            },
            "properties": {
                "observation_date": "2005-03-26",
                "species_reported": "0"
            }
        },
        {
            "type": "Feature",
            "geometry": {
                "type": "Point",
                "coordinates": [
                    -111.589551,
                    38.3932963
                ]
            },
            "properties": {
                "observation_date": "2005-03-25",
                "species_reported": "0"
            }
        },
        {
            "type": "Feature",
            "geometry": {
                "type": "Point",
                "coordinates": [
                    -112.5840282,
                    40.5009431
                ]
            },
            "properties": {
                "observation_date": "2005-03-03",
                "species_reported": "1"
            }
        },
        {
            "type": "Feature",
            "geometry": {
                "type": "Point",
                "coordinates": [
                    -112.6293047,
                    39.1054877
                ]
            },
            "properties": {
                "observation_date": "2005-03-05",
                "species_reported": "0"
            }
        },
        {
            "type": "Feature",
            "geometry": {
                "type": "Point",
                "coordinates": [
                    -112.6293047,
                    39.1054877
                ]
            },
            "properties": {
                "observation_date": "2005-03-05",
                "species_reported": "0"
            }
        },
        {
            "type": "Feature",
            "geometry": {
                "type": "Point",
                "coordinates": [
                    -111.5654755,
                    41.9370197
                ]
            },
            "properties": {
                "observation_date": "2005-03-06",
                "species_reported": "0"
            }
        },
        {
            "type": "Feature",
            "geometry": {
                "type": "Point",
                "coordinates": [
                    -111.6360283,
                    40.2674762
                ]
            },
            "properties": {
                "observation_date": "2005-03-30",
                "species_reported": "0"
            }
        },
        {
            "type": "Feature",
            "geometry": {
                "type": "Point",
                "coordinates": [
                    -111.652422,
                    40.5823447
                ]
            },
            "properties": {
                "observation_date": "2005-03-28",
                "species_reported": "0"
            }
        },
        {
            "type": "Feature",
            "geometry": {
                "type": "Point",
                "coordinates": [
                    -111.8664193,
                    40.7886975
                ]
            },
            "properties": {
                "observation_date": "2005-03-04",
                "species_reported": "0"
            }
        },
        {
            "type": "Feature",
            "geometry": {
                "type": "Point",
                "coordinates": [
                    -112.4212074,
                    40.1801849
                ]
            },
            "properties": {
                "observation_date": "2005-03-12",
                "species_reported": "1"
            }
        },
        {
            "type": "Feature",
            "geometry": {
                "type": "Point",
                "coordinates": [
                    -111.5050926,
                    40.4146087
                ]
            },
            "properties": {
                "observation_date": "2005-03-27",
                "species_reported": "0"
            }
        },
        {
            "type": "Feature",
            "geometry": {
                "type": "Point",
                "coordinates": [
                    -113.5749435,
                    37.0999614
                ]
            },
            "properties": {
                "observation_date": "2005-03-01",
                "species_reported": "0"
            }
        },
        {
            "type": "Feature",
            "geometry": {
                "type": "Point",
                "coordinates": [
                    -113.5749435,
                    37.0999614
                ]
            },
            "properties": {
                "observation_date": "2005-03-02",
                "species_reported": "0"
            }
        },
        {
            "type": "Feature",
            "geometry": {
                "type": "Point",
                "coordinates": [
                    -111.790899,
                    40.704532
                ]
            },
            "properties": {
                "observation_date": "2005-03-06",
                "species_reported": "0"
            }
        },
        {
            "type": "Feature",
            "geometry": {
                "type": "Point",
                "coordinates": [
                    -112.9866922,
                    37.2004753
                ]
            },
            "properties": {
                "observation_date": "2005-03-18",
                "species_reported": "1"
            }
        },
        {
            "type": "Feature",
            "geometry": {
                "type": "Point",
                "coordinates": [
                    -112.9866922,
                    37.2004753
                ]
            },
            "properties": {
                "observation_date": "2005-03-17",
                "species_reported": "1"
            }
        },
        {
            "type": "Feature",
            "geometry": {
                "type": "Point",
                "coordinates": [
                    -112.9866922,
                    37.2004753
                ]
            },
            "properties": {
                "observation_date": "2005-03-15",
                "species_reported": "1"
            }
        },
        {
            "type": "Feature",
            "geometry": {
                "type": "Point",
                "coordinates": [
                    -112.9866922,
                    37.2004753
                ]
            },
            "properties": {
                "observation_date": "2005-03-16",
                "species_reported": "0"
            }
        },
        {
            "type": "Feature",
            "geometry": {
                "type": "Point",
                "coordinates": [
                    -112.9866922,
                    37.2004753
                ]
            },
            "properties": {
                "observation_date": "2005-03-15",
                "species_reported": "1"
            }
        },
        {
            "type": "Feature",
            "geometry": {
                "type": "Point",
                "coordinates": [
                    -112.9472208,
                    37.2903064
                ]
            },
            "properties": {
                "observation_date": "2005-03-16",
                "species_reported": "1"
            }
        },
        {
            "type": "Feature",
            "geometry": {
                "type": "Point",
                "coordinates": [
                    -112.9472208,
                    37.2903064
                ]
            },
            "properties": {
                "observation_date": "2005-03-16",
                "species_reported": "1"
            }
        },
        {
            "type": "Feature",
            "geometry": {
                "type": "Point",
                "coordinates": [
                    -114.037086,
                    39.459949
                ]
            },
            "properties": {
                "observation_date": "2005-03-11",
                "species_reported": "0"
            }
        },
        {
            "type": "Feature",
            "geometry": {
                "type": "Point",
                "coordinates": [
                    -111.195404,
                    38.27821
                ]
            },
            "properties": {
                "observation_date": "2005-03-25",
                "species_reported": "0"
            }
        },
        {
            "type": "Feature",
            "geometry": {
                "type": "Point",
                "coordinates": [
                    -111.6266727,
                    40.2638741
                ]
            },
            "properties": {
                "observation_date": "2005-03-12",
                "species_reported": "0"
            }
        },
        {
            "type": "Feature",
            "geometry": {
                "type": "Point",
                "coordinates": [
                    -113.0006933,
                    37.183057
                ]
            },
            "properties": {
                "observation_date": "2005-03-05",
                "species_reported": "0"
            }
        },
        {
            "type": "Feature",
            "geometry": {
                "type": "Point",
                "coordinates": [
                    -111.8736076,
                    41.7946723
                ]
            },
            "properties": {
                "observation_date": "2005-03-30",
                "species_reported": "1"
            }
        },
        {
            "type": "Feature",
            "geometry": {
                "type": "Point",
                "coordinates": [
                    -111.4614487,
                    40.5157567
                ]
            },
            "properties": {
                "observation_date": "2005-03-16",
                "species_reported": "0"
            }
        }
    ]
}